<?xml version="1.0"?><mxGraphModel><root><mxCell id="0" /><mxCell id="1" parent="0" /><mxCell id="edge1" style="rounded=1;html=1;exitX=0.5;exitY=1;entryX=0.5;entryY=0;jettySize=auto;curved=0;endArrow=block;dashed=0;endFill=1;" parent="1" edge="1" source="node1" target="node2"><mxGeometry as="geometry" relative="1" /></mxCell><mxCell id="edge3" style="rounded=1;html=1;exitX=0.989;exitY=0.382;entryX=1;entryY=0.5;jettySize=auto;curved=1;endArrow=block;dashed=0;endFill=1;" parent="1" edge="1" source="node2" target="node2"><mxGeometry as="geometry" relative="1"><Array as="points"><mxPoint x="354.56" y="1355.79" /><mxPoint x="374.11" y="1372.86" /><mxPoint x="365.05" y="1386.26" /></Array></mxGeometry></mxCell><mxCell id="edge4" style="rounded=1;html=1;exitX=0.0965;exitY=0.799;entryX=0.738;entryY=0;jettySize=auto;curved=0;endArrow=block;dashed=0;endFill=1;" parent="1" edge="1" source="node2" target="node5"><mxGeometry as="geometry" relative="1"><Array as="points"><mxPoint x="225.06" y="1416.23" /><mxPoint x="176.84" y="1463.3799999999999" /><mxPoint x="140.01" y="1519.71" /></Array></mxGeometry></mxCell><mxCell id="edge5" style="rounded=1;html=1;exitX=0.5;exitY=1;entryX=0.5;entryY=0;jettySize=auto;curved=0;endArrow=block;dashed=0;endFill=1;" parent="1" edge="1" source="node2" target="node6"><mxGeometry as="geometry" relative="1" /></mxCell><mxCell id="edge6" style="rounded=1;html=1;exitX=0.897;exitY=0.809;entryX=0.188;entryY=0.0391;jettySize=auto;curved=0;endArrow=block;dashed=0;endFill=1;" parent="1" edge="1" source="node2" target="node7"><mxGeometry as="geometry" relative="1"><Array as="points"><mxPoint x="341.13" y="1417.6799999999998" /><mxPoint x="390.59" y="1463.3799999999999" /><mxPoint x="425.69" y="1505.03" /></Array></mxGeometry></mxCell><mxCell id="edge2" style="rounded=1;html=1;exitX=0.5;exitY=1;entryX=0.5;entryY=0;jettySize=auto;curved=0;endArrow=block;dashed=0;endFill=1;" parent="1" edge="1" source="node4" target="node1"><mxGeometry as="geometry" relative="1" /></mxCell><mxCell id="edge7" style="rounded=1;html=1;exitX=0.692;exitY=0.964;entryX=0.288;entryY=0;jettySize=auto;curved=0;endArrow=block;dashed=0;endFill=1;" parent="1" edge="1" source="node8" target="node9"><mxGeometry as="geometry" relative="1" /></mxCell><mxCell id="edge8" style="rounded=1;html=1;exitX=0.0225;exitY=0.655;entryX=0.209;entryY=0;jettySize=auto;curved=0;endArrow=block;dashed=0;endFill=1;" parent="1" edge="1" source="node9" target="node10"><mxGeometry as="geometry" relative="1"><Array as="points"><mxPoint x="217.21" y="407.14999999999986" /><mxPoint x="58.34" y="529.31" /><mxPoint x="58.34" y="815.0699999999999" /><mxPoint x="321.59" y="866.8199999999999" /><mxPoint x="355.96" y="899.5899999999999" /></Array></mxGeometry></mxCell><mxCell id="edge9" style="rounded=1;html=1;exitX=0.5;exitY=1;entryX=0.5;entryY=0;jettySize=auto;curved=0;endArrow=block;dashed=0;endFill=1;" parent="1" edge="1" source="node9" target="node11"><mxGeometry as="geometry" relative="1" /></mxCell><mxCell id="edge10" style="rounded=1;html=1;exitX=0.862;exitY=0.847;entryX=0.18;entryY=0.0407;jettySize=auto;curved=0;endArrow=block;dashed=0;endFill=1;" parent="1" edge="1" source="node9" target="node12"><mxGeometry as="geometry" relative="1"><Array as="points"><mxPoint x="388.35" y="446.39999999999986" /><mxPoint x="466.59" y="529.31" /><mxPoint x="510.2" y="584.03" /></Array></mxGeometry></mxCell><mxCell id="edge12" style="rounded=1;html=1;exitX=0.252;exitY=0.936;entryX=0.5;entryY=0;jettySize=auto;curved=0;endArrow=block;dashed=0;endFill=1;" parent="1" edge="1" source="node12" target="node10"><mxGeometry as="geometry" relative="1"><Array as="points"><mxPoint x="524.04" y="755.8699999999999" /><mxPoint x="466.59" y="815.0699999999999" /><mxPoint x="407.09" y="833.0699999999999" /><mxPoint x="385.78" y="890.8499999999999" /></Array></mxGeometry></mxCell><mxCell id="edge13" style="rounded=1;html=1;exitX=0.5;exitY=1;entryX=0.5;entryY=0;jettySize=auto;curved=0;endArrow=block;dashed=0;endFill=1;" parent="1" edge="1" source="node12" target="node14"><mxGeometry as="geometry" relative="1" /></mxCell><mxCell id="edge11" style="rounded=1;html=1;exitX=0.5;exitY=0.991;entryX=0.808;entryY=0.0368;jettySize=auto;curved=0;endArrow=block;dashed=0;endFill=1;" parent="1" edge="1" source="node13" target="node9"><mxGeometry as="geometry" relative="1"><Array as="points"><mxPoint x="402.19" y="220.02999999999997" /><mxPoint x="389.59" y="255.63999999999987" /><mxPoint x="377.38" y="281.14999999999986" /></Array></mxGeometry></mxCell><mxCell id="edge14" style="rounded=1;html=1;exitX=0.129;exitY=0.839;entryX=1;entryY=0.16;jettySize=auto;curved=0;endArrow=block;dashed=0;endFill=1;" parent="1" edge="1" source="node14" target="node1"><mxGeometry as="geometry" relative="1"><Array as="points"><mxPoint x="497.11" y="1026.1599999999999" /><mxPoint x="459.59" y="1056.77" /><mxPoint x="351.43" y="1133.65" /></Array></mxGeometry></mxCell><mxCell id="node1" value="&lt;p style='margin:0px;text-align:center;margin-top:4px;;font-size:10.0px;font-family:Times New Roman,serif;color:#000000;'&gt;AvvioChiusura&lt;/p&gt;" style="ellipse;shape=doubleEllipse;aspect=fixed;verticalAlign=top;align=left;overflow=fill;html=1;rounded=0;shadow=0;comic=0;labelBackgroundColor=none;strokeColor=#000000;strokeWidth=1;fillColor=#ffffff;" parent="1" vertex="1"><mxGeometry x="217.55999999999997" y="1112.53" width="132.06" height="132.06" as="geometry" /></mxCell><mxCell id="node2" value="&lt;p style='margin:0px;text-align:center;margin-top:4px;;font-size:10.0px;font-family:Times New Roman,serif;color:#000000;'&gt;VerificaChiusura&lt;/p&gt;" style="ellipse;verticalAlign=top;align=left;overflow=fill;html=1;rounded=0;shadow=0;comic=0;labelBackgroundColor=none;strokeColor=#000000;strokeWidth=1;fillColor=#ffffff;" parent="1" vertex="1"><mxGeometry x="211.07" y="1300.34" width="145.04" height="145.04" as="geometry" /></mxCell><mxCell id="node5" value="&lt;p style='margin:0px;text-align:center;margin-top:4px;;font-size:10.0px;font-family:Times New Roman,serif;color:#000000;'&gt;ChiusuraManuale&lt;/p&gt;" style="ellipse;verticalAlign=top;align=left;overflow=fill;html=1;rounded=0;shadow=0;comic=0;labelBackgroundColor=none;strokeColor=#000000;strokeWidth=1;fillColor=#ffffff;" parent="1" vertex="1"><mxGeometry x="30.070000000000007" y="1523.58" width="149.04" height="149.04" as="geometry" /></mxCell><mxCell id="node6" value="&lt;p style='margin:0px;text-align:center;margin-top:4px;;font-size:10.0px;font-family:Times New Roman,serif;color:#000000;'&gt;ChiusuraAutomatica&lt;/p&gt;" style="ellipse;verticalAlign=top;align=left;overflow=fill;html=1;rounded=0;shadow=0;comic=0;labelBackgroundColor=none;strokeColor=#000000;strokeWidth=1;fillColor=#ffffff;" parent="1" vertex="1"><mxGeometry x="197.59999999999997" y="1512.11" width="171.98" height="171.98" as="geometry" /></mxCell><mxCell id="node7" value="&lt;p style='margin:0px;text-align:center;margin-top:4px;;font-size:10.0px;font-family:Times New Roman,serif;color:#000000;'&gt;EseguiPeriziaIncompleta&lt;/p&gt;" style="ellipse;verticalAlign=top;align=left;overflow=fill;html=1;rounded=0;shadow=0;comic=0;labelBackgroundColor=none;strokeColor=#000000;strokeWidth=1;fillColor=#ffffff;" parent="1" vertex="1"><mxGeometry x="387.63" y="1497.1399999999999" width="201.92" height="201.92" as="geometry" /></mxCell><mxCell id="node3" value="&lt;p style='margin:0px;text-align:center;margin-top:4px;;font-size:10.0px;font-family:Times New Roman,serif;color:#000000;'&gt;Riapertura&lt;/p&gt;" style="ellipse;shape=doubleEllipse;aspect=fixed;verticalAlign=top;align=left;overflow=fill;html=1;rounded=0;shadow=0;comic=0;labelBackgroundColor=none;strokeColor=#000000;strokeWidth=1;fillColor=#ffffff;" parent="1" vertex="1"><mxGeometry x="554.52" y="63.870000000000054" width="98.14" height="98.14" as="geometry" /></mxCell><mxCell id="node4" value="&lt;p style='margin:0px;text-align:center;margin-top:4px;;font-size:10.0px;font-family:Times New Roman,serif;color:#000000;'&gt;Expertise&lt;/p&gt;" style="ellipse;verticalAlign=top;align=left;overflow=fill;html=1;rounded=0;shadow=0;comic=0;labelBackgroundColor=none;strokeColor=#000000;strokeWidth=1;fillColor=#ffffff;" parent="1" vertex="1"><mxGeometry x="222.51" y="916.7199999999999" width="90.16" height="90.16" as="geometry" /></mxCell><mxCell id="node8" value="&lt;p style='margin:0px;text-align:center;margin-top:4px;;font-size:10.0px;font-family:Times New Roman,serif;color:#000000;'&gt;RiaperturaAutomatica&lt;/p&gt;" style="ellipse;verticalAlign=top;align=left;overflow=fill;html=1;rounded=0;shadow=0;comic=0;labelBackgroundColor=none;strokeColor=#000000;strokeWidth=1;fillColor=#ffffff;" parent="1" vertex="1"><mxGeometry x="114.11" y="21.46000000000005" width="182.96" height="182.96" as="geometry" /></mxCell><mxCell id="node9" value="&lt;p style='margin:0px;text-align:center;margin-top:4px;;font-size:10.0px;font-family:Times New Roman,serif;color:#000000;'&gt;SelezioneTipoRiapertura&lt;/p&gt;" style="ellipse;verticalAlign=top;align=left;overflow=fill;html=1;rounded=0;shadow=0;comic=0;labelBackgroundColor=none;strokeColor=#000000;strokeWidth=1;fillColor=#ffffff;" parent="1" vertex="1"><mxGeometry x="212.63" y="273.63999999999993" width="203.92" height="203.92" as="geometry" /></mxCell><mxCell id="node10" value="&lt;p style='margin:0px;text-align:center;margin-top:4px;;font-size:10.0px;font-family:Times New Roman,serif;color:#000000;'&gt;EseguiPerizia&lt;/p&gt;" style="ellipse;verticalAlign=top;align=left;overflow=fill;html=1;rounded=0;shadow=0;comic=0;labelBackgroundColor=none;strokeColor=#000000;strokeWidth=1;fillColor=#ffffff;" parent="1" vertex="1"><mxGeometry x="331.03999999999996" y="902.25" width="119.1" height="119.1" as="geometry" /></mxCell><mxCell id="node11" value="&lt;p style='margin:0px;text-align:center;margin-top:4px;;font-size:10.0px;font-family:Times New Roman,serif;color:#000000;'&gt;SceltaManualeServizioEseguiPerizia&lt;/p&gt;" style="ellipse;verticalAlign=top;align=left;overflow=fill;html=1;rounded=0;shadow=0;comic=0;labelBackgroundColor=none;strokeColor=#000000;strokeWidth=1;fillColor=#ffffff;" parent="1" vertex="1"><mxGeometry x="171.70999999999998" y="529.3100000000001" width="285.76" height="285.76" as="geometry" /></mxCell><mxCell id="node12" value="&lt;p style='margin:0px;text-align:center;margin-top:4px;;font-size:10.0px;font-family:Times New Roman,serif;color:#000000;'&gt;GestioneContestazione&lt;/p&gt;" style="ellipse;verticalAlign=top;align=left;overflow=fill;html=1;rounded=0;shadow=0;comic=0;labelBackgroundColor=none;strokeColor=#000000;strokeWidth=1;fillColor=#ffffff;" parent="1" vertex="1"><mxGeometry x="475.62" y="576.22" width="191.94" height="191.94" as="geometry" /></mxCell><mxCell id="node14" value="&lt;p style='margin:0px;text-align:center;margin-top:4px;;font-size:10.0px;font-family:Times New Roman,serif;color:#000000;'&gt;FinalizzaContestazione&lt;/p&gt;" style="ellipse;verticalAlign=top;align=left;overflow=fill;html=1;rounded=0;shadow=0;comic=0;labelBackgroundColor=none;strokeColor=#000000;strokeWidth=1;fillColor=#ffffff;" parent="1" vertex="1"><mxGeometry x="472.61" y="866.8199999999999" width="189.96" height="189.96" as="geometry" /></mxCell><mxCell id="node13" value="&lt;p style='margin:0px;text-align:center;margin-top:4px;;font-size:10.0px;font-family:Times New Roman,serif;color:#000000;'&gt;CreazioneManualeIncarico&lt;/p&gt;" style="ellipse;verticalAlign=top;align=left;overflow=fill;html=1;rounded=0;shadow=0;comic=0;labelBackgroundColor=none;strokeColor=#000000;strokeWidth=1;fillColor=#ffffff;" parent="1" vertex="1"><mxGeometry x="314.64" y="3.9900000000000517" width="217.9" height="217.9" as="geometry" /></mxCell></root></mxGraphModel>